cloudtik/__init__.py
cloudtik/core/__init__.py
cloudtik/core/api.py
cloudtik/core/command_executor.py
cloudtik/core/database_provider.py
cloudtik/core/job_waiter.py
cloudtik/core/load_balancer_provider.py
cloudtik/core/node_provider.py
cloudtik/core/runtime.py
cloudtik/core/scaling_policy.py
cloudtik/core/storage_provider.py
cloudtik/core/tags.py
cloudtik/core/workspace_provider.py
cloudtik/core/_private/__init__.py
cloudtik/core/_private/annotations.py
cloudtik/core/_private/call_context.py
cloudtik/core/_private/cli_logger.py
cloudtik/core/_private/concurrent_cache.py
cloudtik/core/_private/constants.py
cloudtik/core/_private/crypto.py
cloudtik/core/_private/database_provider_factory.py
cloudtik/core/_private/debug.py
cloudtik/core/_private/docker.py
cloudtik/core/_private/event_system.py
cloudtik/core/_private/load_balancer_provider_factory.py
cloudtik/core/_private/log_timer.py
cloudtik/core/_private/prometheus_metrics.py
cloudtik/core/_private/provider_factory.py
cloudtik/core/_private/resource_spec.py
cloudtik/core/_private/runtime_factory.py
cloudtik/core/_private/script_registry.py
cloudtik/core/_private/services.py
cloudtik/core/_private/storage_provider_factory.py
cloudtik/core/_private/subprocess_output_util.py
cloudtik/core/_private/utils.py
cloudtik/core/_private/workspace_provider_factory.py
cloudtik/core/_private/cluster/__init__.py
cloudtik/core/_private/cluster/cluster_config.py
cloudtik/core/_private/cluster/cluster_dump.py
cloudtik/core/_private/cluster/cluster_exec.py
cloudtik/core/_private/cluster/cluster_logging.py
cloudtik/core/_private/cluster/cluster_metrics.py
cloudtik/core/_private/cluster/cluster_metrics_updater.py
cloudtik/core/_private/cluster/cluster_operator.py
cloudtik/core/_private/cluster/cluster_scaler.py
cloudtik/core/_private/cluster/cluster_tunnel_request.py
cloudtik/core/_private/cluster/cluster_utils.py
cloudtik/core/_private/cluster/event_summarizer.py
cloudtik/core/_private/cluster/node_availability_tracker.py
cloudtik-1.6.0.dist-info/METADATA
cloudtik-1.6.0.dist-info/WHEEL
cloudtik-1.6.0.dist-info/entry_points.txt
cloudtik-1.6.0.dist-info/top_level.txt
cloudtik-1.6.0.dist-info/RECORD
