Metadata-Version: 2.1
Name: cloudtik
Version: 1.6.0
Summary: CloudTik: a cloud scale platform for distributed analytics and AI on public clouds
Home-page: https://github.com/cloudtik/cloudtik.git
Author: Chen Haifeng
License: Apache 2.0
Keywords: Distributed Cloud Data Analytic AI Spark
Classifier: Programming Language :: Python :: 3.8
Requires-Python: >=3.8
Requires-Dist: attrs
Requires-Dist: colorama
Requires-Dist: click >=7.0
Requires-Dist: cryptography >=3.0.0
Requires-Dist: filelock
Requires-Dist: jsonschema
Requires-Dist: prometheus-client >=0.7.1
Requires-Dist: psutil
Requires-Dist: pyyaml
Requires-Dist: redis >=3.5.0
Requires-Dist: requests
Requires-Dist: smart-open
Requires-Dist: prettytable
Requires-Dist: ipaddr
Requires-Dist: pycryptodomex
Requires-Dist: pyopenssl
Requires-Dist: sshtunnel
Requires-Dist: colorful
Requires-Dist: gpustat
Requires-Dist: gputil
Requires-Dist: cloudpickle
Requires-Dist: dataclasses ; python_version < "3.7"
Requires-Dist: numpy >=1.16 ; python_version < "3.9"
Requires-Dist: numpy >=1.19.3 ; python_version >= "3.9"
Provides-Extra: aks
Requires-Dist: azure-mgmt-rdbms ==10.2.0b8 ; extra == 'aks'
Requires-Dist: azure-mgmt-containerservice ; extra == 'aks'
Requires-Dist: azure-storage-file-datalake ==12.6.0 ; extra == 'aks'
Requires-Dist: kopf ; extra == 'aks'
Requires-Dist: azure-identity ==1.11.0 ; extra == 'aks'
Requires-Dist: adlfs ==2023.1.0 ; extra == 'aks'
Requires-Dist: kubernetes ; extra == 'aks'
Requires-Dist: urllib3 ; extra == 'aks'
Requires-Dist: azure-cli ==2.40.0 ; extra == 'aks'
Requires-Dist: azure-storage-blob ==12.14.1 ; extra == 'aks'
Requires-Dist: azure-mgmt-privatedns ; extra == 'aks'
Provides-Extra: aliyun
Requires-Dist: alibabacloud-tea-openapi ==0.3.7 ; extra == 'aliyun'
Requires-Dist: alibabacloud-vpc20160428 ==2.0.20 ; extra == 'aliyun'
Requires-Dist: alibabacloud-vpcpeer20220101 ==1.0.6 ; extra == 'aliyun'
Requires-Dist: alibabacloud-ecs20140526 ==3.0.4 ; extra == 'aliyun'
Requires-Dist: alibabacloud-ram20150501 ==1.0.3 ; extra == 'aliyun'
Requires-Dist: alibabacloud-oss20190517 ==1.0.5 ; extra == 'aliyun'
Requires-Dist: ossfs ==2023.1.0 ; extra == 'aliyun'
Provides-Extra: all
Requires-Dist: s3fs ==2022.11.0 ; extra == 'all'
Requires-Dist: azure-storage-file-datalake ==12.6.0 ; extra == 'all'
Requires-Dist: huaweicloudsdknat ==3.1.35 ; extra == 'all'
Requires-Dist: alibabacloud-ram20150501 ==1.0.3 ; extra == 'all'
Requires-Dist: huaweicloudsdkims ==3.1.35 ; extra == 'all'
Requires-Dist: alibabacloud-ecs20140526 ==3.0.4 ; extra == 'all'
Requires-Dist: kubernetes ; extra == 'all'
Requires-Dist: urllib3 ; extra == 'all'
Requires-Dist: boto3 ==1.24.59 ; extra == 'all'
Requires-Dist: azure-mgmt-containerservice ; extra == 'all'
Requires-Dist: alibabacloud-oss20190517 ==1.0.5 ; extra == 'all'
Requires-Dist: protobuf ==3.20.3 ; extra == 'all'
Requires-Dist: google-cloud-storage ==2.3.0 ; extra == 'all'
Requires-Dist: huaweicloudsdkeip ==3.1.35 ; extra == 'all'
Requires-Dist: huaweicloudsdkvpc ==3.1.35 ; extra == 'all'
Requires-Dist: ossfs ==2023.1.0 ; extra == 'all'
Requires-Dist: huaweicloudsdkiam ==3.1.35 ; extra == 'all'
Requires-Dist: google-api-python-client ==2.48.0 ; extra == 'all'
Requires-Dist: alibabacloud-vpcpeer20220101 ==1.0.6 ; extra == 'all'
Requires-Dist: alibabacloud-tea-openapi ==0.3.7 ; extra == 'all'
Requires-Dist: gcsfs ==2022.11.0 ; extra == 'all'
Requires-Dist: google-cloud-container ==2.21.0 ; extra == 'all'
Requires-Dist: azure-cli ==2.40.0 ; extra == 'all'
Requires-Dist: azure-mgmt-privatedns ; extra == 'all'
Requires-Dist: azure-mgmt-rdbms ==10.2.0b8 ; extra == 'all'
Requires-Dist: huaweicloudsdkecs ==3.1.35 ; extra == 'all'
Requires-Dist: botocore ; extra == 'all'
Requires-Dist: azure-storage-blob ==12.14.1 ; extra == 'all'
Requires-Dist: esdk-obs-python ==3.22.2 ; extra == 'all'
Requires-Dist: kopf ; extra == 'all'
Requires-Dist: azure-identity ==1.11.0 ; extra == 'all'
Requires-Dist: adlfs ==2023.1.0 ; extra == 'all'
Requires-Dist: alibabacloud-vpc20160428 ==2.0.20 ; extra == 'all'
Provides-Extra: aws
Requires-Dist: boto3 ==1.24.59 ; extra == 'aws'
Requires-Dist: s3fs ==2022.11.0 ; extra == 'aws'
Requires-Dist: botocore ; extra == 'aws'
Provides-Extra: azure
Requires-Dist: azure-cli ==2.40.0 ; extra == 'azure'
Requires-Dist: azure-identity ==1.11.0 ; extra == 'azure'
Requires-Dist: azure-storage-blob ==12.14.1 ; extra == 'azure'
Requires-Dist: azure-storage-file-datalake ==12.6.0 ; extra == 'azure'
Requires-Dist: azure-mgmt-containerservice ; extra == 'azure'
Requires-Dist: azure-mgmt-privatedns ; extra == 'azure'
Requires-Dist: azure-mgmt-rdbms ==10.2.0b8 ; extra == 'azure'
Requires-Dist: adlfs ==2023.1.0 ; extra == 'azure'
Provides-Extra: eks
Requires-Dist: s3fs ==2022.11.0 ; extra == 'eks'
Requires-Dist: botocore ; extra == 'eks'
Requires-Dist: boto3 ==1.24.59 ; extra == 'eks'
Requires-Dist: kopf ; extra == 'eks'
Requires-Dist: urllib3 ; extra == 'eks'
Requires-Dist: kubernetes ; extra == 'eks'
Provides-Extra: gcp
Requires-Dist: google-api-python-client ==2.48.0 ; extra == 'gcp'
Requires-Dist: google-cloud-storage ==2.3.0 ; extra == 'gcp'
Requires-Dist: google-cloud-container ==2.21.0 ; extra == 'gcp'
Requires-Dist: gcsfs ==2022.11.0 ; extra == 'gcp'
Requires-Dist: protobuf ==3.20.3 ; extra == 'gcp'
Provides-Extra: gke
Requires-Dist: google-api-python-client ==2.48.0 ; extra == 'gke'
Requires-Dist: kopf ; extra == 'gke'
Requires-Dist: protobuf ==3.20.3 ; extra == 'gke'
Requires-Dist: gcsfs ==2022.11.0 ; extra == 'gke'
Requires-Dist: google-cloud-storage ==2.3.0 ; extra == 'gke'
Requires-Dist: google-cloud-container ==2.21.0 ; extra == 'gke'
Requires-Dist: kubernetes ; extra == 'gke'
Requires-Dist: urllib3 ; extra == 'gke'
Provides-Extra: huaweicloud
Requires-Dist: huaweicloudsdkecs ==3.1.35 ; extra == 'huaweicloud'
Requires-Dist: huaweicloudsdkvpc ==3.1.35 ; extra == 'huaweicloud'
Requires-Dist: huaweicloudsdknat ==3.1.35 ; extra == 'huaweicloud'
Requires-Dist: huaweicloudsdkeip ==3.1.35 ; extra == 'huaweicloud'
Requires-Dist: huaweicloudsdkiam ==3.1.35 ; extra == 'huaweicloud'
Requires-Dist: huaweicloudsdkims ==3.1.35 ; extra == 'huaweicloud'
Requires-Dist: esdk-obs-python ==3.22.2 ; extra == 'huaweicloud'
Provides-Extra: kubernetes
Requires-Dist: kubernetes ; extra == 'kubernetes'
Requires-Dist: urllib3 ; extra == 'kubernetes'
Requires-Dist: kopf ; extra == 'kubernetes'
